main.py
openai_secrets_manager-0.1.0.dist-info/METADATA
openai_secrets_manager-0.1.0.dist-info/WHEEL
openai_secrets_manager-0.1.0.dist-info/top_level.txt
openai_secrets_manager-0.1.0.dist-info/RECORD
